pycarta/__init__.py
pycarta/exceptions.py
pycarta/admin/__init__.py
pycarta/admin/file.py
pycarta/admin/group.py
pycarta/admin/permission.py
pycarta/admin/project.py
pycarta/admin/secret.py
pycarta/admin/service.py
pycarta/admin/user.py
pycarta/admin/workspace.py
pycarta/admin/types/__init__.py
pycarta/admin/types/connection.py
pycarta/admin/types/document_history.py
pycarta/admin/types/file.py
pycarta/admin/types/group.py
pycarta/admin/types/item.py
pycarta/admin/types/namespace.py
pycarta/admin/types/permission_entity.py
pycarta/admin/types/permissions.py
pycarta/admin/types/project.py
pycarta/admin/types/resource_type.py
pycarta/admin/types/service.py
pycarta/admin/types/user.py
pycarta/admin/types/util.py
pycarta/admin/types/workspace.py
pycarta/auth/__init__.py
pycarta/auth/agent.py
pycarta/auth/config.py
pycarta/auth/profile.py
pycarta/auth/ui.py
pycarta/auth/weblogin.py
pycarta/auth/dialogs/carta_login.py
pycarta/formsdb/__init__.py
pycarta/formsdb/types.py
pycarta/fs/__init__.py
pycarta/fs/configuration.py
pycarta/fs/file.py
pycarta/fs/multipart_upload.py
pycarta/fs/types/__init__.py
pycarta/fs/types/configuration.py
pycarta/fs/types/exception.py
pycarta/fs/types/file.py
pycarta/graph/__init__.py
pycarta/graph/algorithms.py
pycarta/graph/graph.py
pycarta/graph/iterator.py
pycarta/graph/util.py
pycarta/graph/vertex/__init__.py
pycarta/graph/vertex/types.py
pycarta/graph/vertex/util.py
pycarta/graph/visitor/__init__.py
pycarta/graph/visitor/base.py
pycarta/mqtt/__init__.py
pycarta/mqtt/client.py
pycarta/mqtt/connection.py
pycarta/mqtt/credentials.py
pycarta/mqtt/exceptions.py
pycarta/mqtt/formatter.py
pycarta/mqtt/publisher.py
pycarta/mqtt/subscriber.py
pycarta/sbg/__init__.py
pycarta/sbg/base.py
pycarta/sbg/login.py
pycarta/sbg/project.py
pycarta/services/__init__.py
pycarta/services/proxy.py
pycarta/services/server.py
pycarta/tablify/__init__.py
pycarta/tablify/__main__.py
pycarta/tablify/core.py
pycarta/tablify/io.py
pycarta/tablify/melt.py
pycarta-0.3.8.dist-info/licenses/LICENSE.txt
pycarta-0.3.8.dist-info/METADATA
pycarta-0.3.8.dist-info/WHEEL
pycarta-0.3.8.dist-info/top_level.txt
pycarta-0.3.8.dist-info/RECORD
