Metadata-Version: 2.4
Name: pycarta
Version: 0.3.8
Summary: Python interface to Carta.
Author: Branden Kappes
Author-email: branden.kappes@contextualize.us.com
License: MIT
Platform: any
Classifier: Development Status :: 4 - Beta
Classifier: Programming Language :: Python
Requires-Python: >=3.12
License-File: LICENSE.txt
Requires-Dist: importlib-metadata
Requires-Dist: aiomqtt
Requires-Dist: authlib
Requires-Dist: boto3
Requires-Dist: fastapi[standard]
Requires-Dist: inflection
Requires-Dist: itsdangerous
Requires-Dist: networkx
Requires-Dist: numpy
Requires-Dist: paho-mqtt
Requires-Dist: pandas
Requires-Dist: pycognito
Requires-Dist: pydantic
Requires-Dist: python-dotenv
Requires-Dist: sevenbridges-python
Requires-Dist: starlette
Requires-Dist: tqdm
Requires-Dist: uvicorn
Requires-Dist: websockets
Provides-Extra: develop
Requires-Dist: ipython; extra == "develop"
Requires-Dist: jupyter; extra == "develop"
Requires-Dist: jupyterlab; extra == "develop"
Requires-Dist: pydot; extra == "develop"
Provides-Extra: testing
Requires-Dist: fastapi; extra == "testing"
Requires-Dist: flask; extra == "testing"
Requires-Dist: petname; extra == "testing"
Requires-Dist: pytest; extra == "testing"
Requires-Dist: pytest-cov; extra == "testing"
Requires-Dist: setuptools; extra == "testing"
Requires-Dist: pytest-asyncio; extra == "testing"
Requires-Dist: pytest-dependency; extra == "testing"
Dynamic: license-file
